README.rst
setup.py
nonebot_plugin_chatgpt_on_qq/__init__.py
nonebot_plugin_chatgpt_on_qq/apikey.py
nonebot_plugin_chatgpt_on_qq/config.py
nonebot_plugin_chatgpt_on_qq/custom_errors.py
nonebot_plugin_chatgpt_on_qq/loadpresets.py
nonebot_plugin_chatgpt_on_qq/sessions.py
nonebot_plugin_chatgpt_on_qq.egg-info/PKG-INFO
nonebot_plugin_chatgpt_on_qq.egg-info/SOURCES.txt
nonebot_plugin_chatgpt_on_qq.egg-info/dependency_links.txt
nonebot_plugin_chatgpt_on_qq.egg-info/requires.txt
nonebot_plugin_chatgpt_on_qq.egg-info/top_level.txt