Metadata-Version: 2.1
Name: nonebot-plugin-chatgpt-on-qq
Version: 1.6.2
Summary: 具有多对话功能的chatGPT聊天插件
Home-page: https://github.com/Suxmx/nonebot_plugin_chatgpt_turbo_on_qq
Author: 颜曦
Author-email: 424504326@qq.com
Maintainer: 颜曦
Maintainer-email: 424504326@qq.com
License: BSD License
Platform: all
Classifier: Development Status :: 4 - Beta
Classifier: Operating System :: OS Independent
Classifier: Intended Audience :: Developers
Classifier: License :: OSI Approved :: BSD License
Classifier: Programming Language :: Python
Classifier: Programming Language :: Python :: 3.10
Classifier: Programming Language :: Python :: Implementation :: CPython
Classifier: Programming Language :: Python :: Implementation :: PyPy
